ervision/__init__.py
ervision-0.0.1.dist-info/LICENSE
ervision-0.0.1.dist-info/METADATA
ervision-0.0.1.dist-info/WHEEL
ervision-0.0.1.dist-info/top_level.txt
ervision-0.0.1.dist-info/RECORD
