Metadata-Version: 2.1
Name: ervision
Version: 0.0.1
Summary: Computer Vision library tools and helper
Author-email: Lalu Erfandi Maula Yusnu <nunenuh@gmail.com>
License: MIT License        
Project-URL: Homepage, https://github.com/nunenuh/ervision
Project-URL: Bug Tracker, https://github.com/nunenuh/ervision/issues
Classifier: Programming Language :: Python :: 3
Classifier: License :: OSI Approved :: MIT License
Classifier: Operating System :: OS Independent
Requires-Python: >=3.8
License-File: LICENSE
